hidebehind/__init__.py
hidebehind/__main__.py
hidebehind/binutils.py
hidebehind/image.py
hidebehind/main.py
hidebehind/secret.py
hidebehind-0.0.2.dist-info/LICENSE
hidebehind-0.0.2.dist-info/METADATA
hidebehind-0.0.2.dist-info/WHEEL
hidebehind-0.0.2.dist-info/entry_points.txt
hidebehind-0.0.2.dist-info/top_level.txt
hidebehind-0.0.2.dist-info/RECORD
