Metadata-Version: 2.1
Name: hidebehind
Version: 0.0.2
Summary: A steganography library
Home-page: https://github.com/multifrench/hidebehind
Author: multifrench
Author-email: multifrench@protonmail.com
License: UNKNOWN
Project-URL: Bug Tracker, https://github.com/multifrench/hidebehind/issues
Platform: UNKNOWN
Classifier: Programming Language :: Python :: 3
Classifier: Environment :: Console
Classifier: Intended Audience :: Education
Classifier: Topic :: Security
Classifier: Natural Language :: English
Classifier: License :: OSI Approved :: GNU Lesser General Public License v3 (LGPLv3)
Classifier: Operating System :: POSIX :: Linux
Requires-Python: >=3.9
Requires-Dist: numpy
Requires-Dist: Pillow
